PipeDSL/__init__.py
PipeDSL/lexer.py
PipeDSL/models.py
PipeDSL/services/__init__.py
PipeDSL/services/generate_task.py
PipeDSL/services/task_scheduler.py
PipeDSL/utils/__init__.py
PipeDSL/utils/http_client.py
PipeDSL/utils/logger.py
PipeDSL/utils/utils.py
PipeDSL/utils/tests/test_utils.py
pipedsl-0.1.9.dist-info/METADATA
pipedsl-0.1.9.dist-info/WHEEL
pipedsl-0.1.9.dist-info/RECORD
