Metadata-Version: 2.4
Name: PipeDSL
Version: 0.1.9
Author-email: Your Name <you@example.com>
Requires-Python: <4.0,>=3.13
Requires-Dist: aiohttp<4.0.0,>=3.12.15
Requires-Dist: coverage<8.0.0,>=7.10.6
Requires-Dist: jsonpath-ng<2.0.0,>=1.7.0
Requires-Dist: nltk<3.9.2,>=3.9.1
Requires-Dist: pydantic<3.0.0,>=2.10.6
Requires-Dist: pytest-cov<8.0.0,>=7.0.0
Requires-Dist: pytest<9.0.0,>=8.3.5
Requires-Dist: pyyaml<7.0.0,>=6.0.2
